blizworkapi.py
blizworkapi-0.0.5.dist-info/METADATA
blizworkapi-0.0.5.dist-info/WHEEL
blizworkapi-0.0.5.dist-info/top_level.txt
blizworkapi-0.0.5.dist-info/RECORD
