Metadata-Version: 2.1
Name: blizworkapi
Version: 0.0.5
Summary: Python wrapper for the BlizWork API
Home-page: UNKNOWN
Author: Edo Elk
License: UNKNOWN
Platform: UNKNOWN
Classifier: Programming Language :: Python :: 3
Classifier: License :: OSI Approved :: MIT License
Classifier: Operating System :: OS Independent
Requires-Python: >=3.9
Requires-Dist: requests
